fotmob/__init__.py
fotmob/api.py
fotmob/utils/__init__.py
fotmob/utils/ls_x.py
fotmob_wrapper-0.0.5.dist-info/licenses/LICENSE
fotmob_wrapper-0.0.5.dist-info/METADATA
fotmob_wrapper-0.0.5.dist-info/WHEEL
fotmob_wrapper-0.0.5.dist-info/top_level.txt
fotmob_wrapper-0.0.5.dist-info/RECORD
