Metadata-Version: 2.4
Name: fotmob-wrapper
Version: 0.0.5
Summary: Python API wrapper for FotMob undocumented API
Home-page: https://github.com/tommhe14/fotmob-wrapper
Author: tommhe14
Author-email: theckley@yahoo.co.uk
License: MIT
Project-URL: Bug Reports, https://github.com/tommhe14/fotmob-wrapper
Project-URL: Source, https://github.com/tommhe14/fotmob-wrapper
Keywords: transfermarkt tmk football soccer fotmob sofascore flashscore api wrapper fotmob
Classifier: Development Status :: 3 - Alpha
Classifier: Intended Audience :: Developers
Classifier: License :: OSI Approved :: MIT License
Classifier: Programming Language :: Python :: 3.8
Classifier: Programming Language :: Python :: 3.9
Classifier: Programming Language :: Python :: 3.10
Classifier: Programming Language :: Python :: 3.11
Classifier: Topic :: Software Development :: Libraries :: Python Modules
Requires-Python: >=3.8
License-File: LICENSE
Requires-Dist: aiohttp>=3.8.0
Dynamic: author
Dynamic: author-email
Dynamic: classifier
Dynamic: description
Dynamic: description-content-type
Dynamic: home-page
Dynamic: keywords
Dynamic: license
Dynamic: license-file
Dynamic: project-url
Dynamic: requires-dist
Dynamic: requires-python
Dynamic: summary
